pytoolbox/__init__.py
pytoolbox/argparse.py
pytoolbox/atlassian.py
pytoolbox/collections.py
pytoolbox/comparison.py
pytoolbox/console.py
pytoolbox/crypto.py
pytoolbox/datetime.py
pytoolbox/decorators.py
pytoolbox/enum.py
pytoolbox/exceptions.py
pytoolbox/filesystem.py
pytoolbox/flask.py
pytoolbox/git.py
pytoolbox/humanize.py
pytoolbox/itertools.py
pytoolbox/juju.py
pytoolbox/linux.py
pytoolbox/logging.py
pytoolbox/module.py
pytoolbox/pandas.py
pytoolbox/private.py
pytoolbox/regex.py
pytoolbox/serialization.py
pytoolbox/setuptools.py
pytoolbox/signals.py
pytoolbox/ssh.py
pytoolbox/states.py
pytoolbox/string.py
pytoolbox/subprocess.py
pytoolbox/throttles.py
pytoolbox/types.py
pytoolbox/unittest.py
pytoolbox/validation.py
pytoolbox/virtualenv.py
pytoolbox/voluptuous.py
pytoolbox/ai/__init__.py
pytoolbox/ai/vision/__init__.py
pytoolbox/ai/vision/utils.py
pytoolbox/ai/vision/face/__init__.py
pytoolbox/ai/vision/face/detect/__init__.py
pytoolbox/ai/vision/face/detect/dlib.py
pytoolbox/ai/vision/face/recognize/__init__.py
pytoolbox/ai/vision/face/recognize/nn4_small2.py
pytoolbox/aws/__init__.py
pytoolbox/aws/s3.py
pytoolbox/django/__init__.py
pytoolbox/django/storage.py
pytoolbox/django/templatetags.py
pytoolbox/django/urls.py
pytoolbox/django/core/__init__.py
pytoolbox/django/core/constants.py
pytoolbox/django/core/exceptions.py
pytoolbox/django/core/validators.py
pytoolbox/django/forms/__init__.py
pytoolbox/django/forms/base.py
pytoolbox/django/forms/fields.py
pytoolbox/django/forms/mixins.py
pytoolbox/django/forms/utils.py
pytoolbox/django/forms/widgets.py
pytoolbox/django/models/__init__.py
pytoolbox/django/models/base.py
pytoolbox/django/models/decorators.py
pytoolbox/django/models/metaclass.py
pytoolbox/django/models/mixins.py
pytoolbox/django/models/utils.py
pytoolbox/django/models/fields/__init__.py
pytoolbox/django/models/fields/base.py
pytoolbox/django/models/fields/mixins.py
pytoolbox/django/models/managers/__init__.py
pytoolbox-14.8.6.dist-info/AUTHORS.md
pytoolbox-14.8.6.dist-info/LICENSE.rst
pytoolbox-14.8.6.dist-info/METADATA
pytoolbox-14.8.6.dist-info/WHEEL
pytoolbox-14.8.6.dist-info/top_level.txt
pytoolbox-14.8.6.dist-info/RECORD
