Metadata-Version: 2.1
Name: pytoolbox
Version: 14.8.6
Summary: Toolbox for Python scripts
Home-page: https://github.com/davidfischer-ch/pytoolbox
Author: David Fischer
Author-email: david@fisch3r.net
License: EUPL 1.1
Keywords: celery,ffmpeg,django,flask,json,juju,mock,pillow,rsync,rtp,selenium,smpte 2022-1,screen,subprocess
Classifier: Development Status :: 5 - Production/Stable
Classifier: Intended Audience :: Developers
Classifier: Framework :: Django
Classifier: Framework :: Flask
Classifier: License :: OSI Approved :: European Union Public Licence 1.1 (EUPL 1.1)
Classifier: Natural Language :: English
Classifier: Operating System :: POSIX :: Linux
Classifier: Programming Language :: Python
Classifier: Programming Language :: Python :: 3
Classifier: Programming Language :: Python :: 3.11
Classifier: Programming Language :: Python :: 3.12
Classifier: Programming Language :: Python :: Implementation :: CPython
Classifier: Programming Language :: Python :: Implementation :: PyPy
Classifier: Topic :: Software Development :: Libraries :: Python Modules
Requires-Python: >=3.11
License-File: LICENSE.rst
License-File: AUTHORS.md
Requires-Dist: argparse
Requires-Dist: python-magic
Requires-Dist: pytz
Requires-Dist: requests
Requires-Dist: ruamel.yaml
Requires-Dist: termcolor
Provides-Extra: all
Requires-Dist: PyGObject; extra == "all"
Requires-Dist: boto3; extra == "all"
Requires-Dist: django; extra == "all"
Requires-Dist: django-filter; extra == "all"
Requires-Dist: django-formtools; extra == "all"
Requires-Dist: django-oauth-toolkit; extra == "all"
Requires-Dist: djangorestframework>=3; extra == "all"
Requires-Dist: dlib; extra == "all"
Requires-Dist: ezodf; extra == "all"
Requires-Dist: fastxor; extra == "all"
Requires-Dist: flask; extra == "all"
Requires-Dist: jinja2; extra == "all"
Requires-Dist: jira; extra == "all"
Requires-Dist: keras; extra == "all"
Requires-Dist: lxml; extra == "all"
Requires-Dist: numpy; extra == "all"
Requires-Dist: opencv-python; extra == "all"
Requires-Dist: pandas; extra == "all"
Requires-Dist: pillow; extra == "all"
Requires-Dist: pymongo; extra == "all"
Requires-Dist: selenium; extra == "all"
Requires-Dist: tensorflow; extra == "all"
Requires-Dist: tldextract; extra == "all"
Requires-Dist: voluptuous; extra == "all"
Provides-Extra: atlassian
Requires-Dist: jira; extra == "atlassian"
Provides-Extra: aws
Requires-Dist: boto3; extra == "aws"
Provides-Extra: django
Requires-Dist: django; extra == "django"
Provides-Extra: django_filter
Requires-Dist: django-filter; extra == "django-filter"
Provides-Extra: django_formtools
Requires-Dist: django-formtools; extra == "django-formtools"
Provides-Extra: doc
Requires-Dist: sphinx>=7.2.6; extra == "doc"
Requires-Dist: sphinx-rtd-theme>=2.0.0; extra == "doc"
Provides-Extra: flask
Requires-Dist: flask; extra == "flask"
Provides-Extra: imaging
Requires-Dist: pillow; extra == "imaging"
Requires-Dist: PyGObject; extra == "imaging"
Provides-Extra: jinja2
Requires-Dist: jinja2; extra == "jinja2"
Provides-Extra: mongodb
Requires-Dist: pymongo; extra == "mongodb"
Provides-Extra: network
Requires-Dist: tldextract; extra == "network"
Provides-Extra: pandas
Requires-Dist: ezodf; extra == "pandas"
Requires-Dist: lxml; extra == "pandas"
Requires-Dist: pandas; extra == "pandas"
Provides-Extra: rest_framework
Requires-Dist: django-oauth-toolkit; extra == "rest-framework"
Requires-Dist: djangorestframework>=3; extra == "rest-framework"
Provides-Extra: selenium
Requires-Dist: selenium; extra == "selenium"
Provides-Extra: smpte2022
Requires-Dist: fastxor; extra == "smpte2022"
Provides-Extra: test
Requires-Dist: colored>=2.2.4; extra == "test"
Requires-Dist: coverage>=7.4.4; extra == "test"
Requires-Dist: flake8>=7.0.0; extra == "test"
Requires-Dist: mypy>=1.9.0; extra == "test"
Requires-Dist: pylint>=3.1.0; extra == "test"
Requires-Dist: pytest>=8.1.1; extra == "test"
Requires-Dist: pytest-cov>=4.1.0; extra == "test"
Requires-Dist: pytest-pylint>=0.21.0; extra == "test"
Requires-Dist: pytest-ruff>=0.3.1; extra == "test"
Requires-Dist: ruff>=0.3.3; extra == "test"
Requires-Dist: PyGObject-stubs>=2.10.0; extra == "test"
Requires-Dist: types-pytz>=2024.1.0.20240203; extra == "test"
Requires-Dist: types-requests>=2.31.0.20240311; extra == "test"
Requires-Dist: types-urllib3>=1.26.25.14; extra == "test"
Provides-Extra: vision
Requires-Dist: dlib; extra == "vision"
Requires-Dist: keras; extra == "vision"
Requires-Dist: numpy; extra == "vision"
Requires-Dist: opencv-python; extra == "vision"
Requires-Dist: tensorflow; extra == "vision"
Provides-Extra: voluptuous
Requires-Dist: voluptuous; extra == "voluptuous"
